cf_shield/__init__.py
cf_shield/main.py
cf_shield-0.2.0.dist-info/licenses/LICENSE
cf_shield-0.2.0.dist-info/METADATA
cf_shield-0.2.0.dist-info/WHEEL
cf_shield-0.2.0.dist-info/entry_points.txt
cf_shield-0.2.0.dist-info/top_level.txt
cf_shield-0.2.0.dist-info/RECORD
