Metadata-Version: 2.4
Name: cf-shield
Version: 0.2.0
Summary: CF-Shield is a Python script for detecting DDoS attacks and enabling security measures on Cloudflare automatically.
Author-email: Sakura-sx <sakura@voxga.xyz>
License-Expression: GPL-3.0
Project-URL: Homepage, https://github.com/Sakura-sx/cf-shield
Project-URL: Issues, https://github.com/Sakura-sx/cf-shield/issues
Project-URL: Repository, https://github.com/Sakura-sx/cf-shield
Classifier: Development Status :: 5 - Production/Stable
Classifier: Intended Audience :: System Administrators
Classifier: Intended Audience :: Developers
Classifier: Operating System :: OS Independent
Classifier: Programming Language :: Python :: 3
Classifier: Programming Language :: Python :: 3.8
Classifier: Programming Language :: Python :: 3.9
Classifier: Programming Language :: Python :: 3.10
Classifier: Programming Language :: Python :: 3.11
Classifier: Programming Language :: Python :: 3.12
Classifier: Topic :: Internet
Classifier: Topic :: Internet :: WWW/HTTP :: Dynamic Content
Classifier: Topic :: System :: Monitoring
Classifier: Topic :: System :: Systems Administration
Requires-Python: >=3.8
License-File: LICENSE
Requires-Dist: psutil
Requires-Dist: cloudflare
Requires-Dist: python-dotenv
Requires-Dist: discord-webhook
Requires-Dist: colorlog
Requires-Dist: requests
Requires-Dist: logging
Requires-Dist: slack_sdk
Dynamic: license-file
